{
  "exp_name": "build_local_conflict_set_predictor_dataset",
  "dataset_tag": "official_bytetrack_editutility_trainhalf_largecover",
  "feature_version": "v2_hostnorm_geom",
  "teacher_mode": "edit_utility",
  "edit_utility_commit_cost": 0.2,
  "edit_utility_min_gain": 0.75,
  "edit_utility_force_defer_gain": 0.5,
  "runtime_host_match_thresh": 0.9,
  "soft_rescue_weight": 0.75,
  "rescue_force_defer_gain": 0.5,
  "rescue_min_gain": 0.5,
  "large_component_max_subclusters": 3,
  "source_manifest": "/gemini/code/FMtrack-main/FM-Track/outputs/official_bytetrack_editutility_rawgate_select_v1_20260326_143126/source_manifest.csv",
  "sources": 1,
  "source_frames": 2657,
  "frames": 1130,
  "unused_frames": 1527,
  "raw_components": 1130,
  "eligible_clusters": 1130,
  "oversized_components": 573,
  "recovered_large_components": 573,
  "mined_large_subclusters": 573,
  "mined_component_clusters": 573,
  "frames_with_eligible_clusters": 1130,
  "trigger_pass_clusters": 1126,
  "trigger_fail_clusters": 4,
  "committed_matches": 56,
  "cluster_should_intervene_clusters": 361,
  "cluster_utility_gain": 755.3000000000001,
  "cluster_edit_gain": 766.5,
  "cluster_edit_cost": 11.199999999999992,
  "cluster_edit_utility_gain": 755.3000000000001,
  "cluster_should_intervene_soft_clusters": 46,
  "cluster_soft_utility_gain": 45.0,
  "host_equals_oracle_clusters": 476,
  "host_runtime_equals_oracle_clusters": 549,
  "host_committed_matches": 8254,
  "host_runtime_committed_matches": 7966,
  "oracle_committed_matches": 6834,
  "delta_committed_matches": 56,
  "edit_committed_matches": 56,
  "rescue_committed_matches": 57,
  "hard_delta_committed_matches": 9,
  "soft_rescue_committed_matches": 48,
  "edit_rows": 1477,
  "rescue_rows": 57,
  "add_commit_rows": 1,
  "reassign_rows": 55,
  "force_defer_rows": 1421,
  "hard_delta_rows": 9,
  "soft_rescue_rows": 48,
  "rescue_force_defer_rows": 1141,
  "detections": 8273,
  "tracks": 12174,
  "edges": 65471,
  "skipped_large_clusters": 573,
  "train_sequences": "MOT17-05-FRCNN,MOT17-09-FRCNN",
  "val_sequences": "MOT17-11-FRCNN",
  "host_variants": "official_bytetrack",
  "source_tags": "official_bytetrack_trainhalf",
  "det_feature_dim": 9,
  "track_feature_dim": 8,
  "edge_feature_dim": 18,
  "cluster_feature_dim": 11,
  "status": "ok",
  "split_breakdown": {
    "train": {
      "frames": 680,
      "raw_components": 680,
      "skipped_large_clusters": 222,
      "oversized_components": 222,
      "mined_large_subclusters": 222,
      "frames_with_eligible_clusters": 680,
      "eligible_clusters": 680,
      "mined_component_clusters": 222,
      "detections": 4738,
      "tracks": 6799,
      "edges": 37191,
      "trigger_pass_clusters": 680,
      "committed_matches": 48,
      "cluster_should_intervene_clusters": 205,
      "cluster_utility_gain": 431.40000000000015,
      "cluster_edit_gain": 441.0,
      "cluster_edit_cost": 9.599999999999998,
      "cluster_edit_utility_gain": 431.40000000000015,
      "cluster_should_intervene_soft_clusters": 38,
      "cluster_soft_utility_gain": 39.0,
      "host_equals_oracle_clusters": 284,
      "host_runtime_equals_oracle_clusters": 333,
      "host_committed_matches": 4719,
      "host_runtime_committed_matches": 4526,
      "oracle_committed_matches": 3934,
      "delta_committed_matches": 48,
      "edit_committed_matches": 48,
      "rescue_committed_matches": 49,
      "hard_delta_committed_matches": 9,
      "soft_rescue_committed_matches": 40,
      "edit_rows": 834,
      "rescue_rows": 49,
      "add_commit_rows": 1,
      "reassign_rows": 47,
      "force_defer_rows": 786,
      "hard_delta_rows": 9,
      "soft_rescue_rows": 40,
      "rescue_force_defer_rows": 601,
      "recovered_large_components": 222
    },
    "val": {
      "recovered_large_components": 351,
      "frames": 450,
      "raw_components": 450,
      "skipped_large_clusters": 351,
      "oversized_components": 351,
      "mined_large_subclusters": 351,
      "frames_with_eligible_clusters": 450,
      "eligible_clusters": 450,
      "mined_component_clusters": 351,
      "detections": 3535,
      "tracks": 5375,
      "edges": 28280,
      "trigger_pass_clusters": 446,
      "committed_matches": 8,
      "cluster_should_intervene_clusters": 156,
      "cluster_utility_gain": 323.9,
      "cluster_edit_gain": 325.5,
      "cluster_edit_cost": 1.5999999999999999,
      "cluster_edit_utility_gain": 323.9,
      "cluster_should_intervene_soft_clusters": 8,
      "cluster_soft_utility_gain": 6.0,
      "host_equals_oracle_clusters": 192,
      "host_runtime_equals_oracle_clusters": 216,
      "host_committed_matches": 3535,
      "host_runtime_committed_matches": 3440,
      "oracle_committed_matches": 2900,
      "delta_committed_matches": 8,
      "edit_committed_matches": 8,
      "rescue_committed_matches": 8,
      "hard_delta_committed_matches": 0,
      "soft_rescue_committed_matches": 8,
      "edit_rows": 643,
      "rescue_rows": 8,
      "add_commit_rows": 0,
      "reassign_rows": 8,
      "force_defer_rows": 635,
      "hard_delta_rows": 0,
      "soft_rescue_rows": 8,
      "rescue_force_defer_rows": 540
    }
  },
  "sequences": [
    "MOT17-05-FRCNN",
    "MOT17-09-FRCNN",
    "MOT17-11-FRCNN"
  ]
}
